fast_sentence_classify/__init__.py
fast_sentence_classify/core/__init__.py
fast_sentence_classify/core/bp/__init__.py
fast_sentence_classify/core/bp/classifier.py
fast_sentence_classify/core/dmo/__init__.py
fast_sentence_classify/core/svc/__init__.py
fast_sentence_classify/core/svc/find_classification_evidence.py
fast_sentence_classify/datablock/__init__.py
fast_sentence_classify/datablock/dmo/__init__.py
fast_sentence_classify/datablock/dto/__init__.py
fast_sentence_classify/datablock/dto/basic_how_kb.py
fast_sentence_classify/datablock/dto/basic_what_kb.py
fast_sentence_classify/datablock/dto/basic_where_kb.py
fast_sentence_classify/datablock/dto/existential_kb.py
fast_sentence_classify/datablock/dto/hints_kb.py
fast_sentence_classify/datablock/dto/how_long_time_kb.py
fast_sentence_classify/datablock/dto/how_many_kb.py
fast_sentence_classify/datablock/dto/how_much_money_kb.py
fast_sentence_classify/datablock/dto/what_when_kb.py
fast_sentence_classify/datablock/dto/what_who_kb.py
fast_sentence_classify/datablock/dto/what_will_kb.py
fast_sentence_classify/datablock/dto/when_date_kb.py
fast_sentence_classify/datablock/dto/where_location_kb.py
fast_sentence_classify/datablock/svc/__init__.py
fast_sentence_classify/datablock/svc/find_classification_hints.py
fast_sentence_classify-0.1.7.dist-info/WHEEL
fast_sentence_classify-0.1.7.dist-info/METADATA
fast_sentence_classify-0.1.7.dist-info/RECORD
